{
  "build": "pyhd8ed1ab_0",
  "build_number": 0,
  "channel": "https://conda.anaconda.org/conda-forge/noarch",
  "constrains": [],
  "depends": [
    "python ==2.7.*|>=3.5"
  ],
  "extracted_package_dir": "/opt/homebrew/Caskroom/miniforge/base/pkgs/pycodestyle-2.8.0-pyhd8ed1ab_0",
  "features": "",
  "files": [
    "lib/python3.9/site-packages/pycodestyle-2.8.0.dist-info/INSTALLER",
    "lib/python3.9/site-packages/pycodestyle-2.8.0.dist-info/LICENSE",
    "lib/python3.9/site-packages/pycodestyle-2.8.0.dist-info/METADATA",
    "lib/python3.9/site-packages/pycodestyle-2.8.0.dist-info/RECORD",
    "lib/python3.9/site-packages/pycodestyle-2.8.0.dist-info/REQUESTED",
    "lib/python3.9/site-packages/pycodestyle-2.8.0.dist-info/WHEEL",
    "lib/python3.9/site-packages/pycodestyle-2.8.0.dist-info/direct_url.json",
    "lib/python3.9/site-packages/pycodestyle-2.8.0.dist-info/entry_points.txt",
    "lib/python3.9/site-packages/pycodestyle-2.8.0.dist-info/namespace_packages.txt",
    "lib/python3.9/site-packages/pycodestyle-2.8.0.dist-info/top_level.txt",
    "lib/python3.9/site-packages/pycodestyle.py",
    "lib/python3.9/site-packages/__pycache__/pycodestyle.cpython-39.pyc",
    "bin/pycodestyle"
  ],
  "fn": "pycodestyle-2.8.0-pyhd8ed1ab_0.tar.bz2",
  "license": "MIT",
  "license_family": "MIT",
  "link": {
    "source": "/opt/homebrew/Caskroom/miniforge/base/pkgs/pycodestyle-2.8.0-pyhd8ed1ab_0",
    "type": 1
  },
  "md5": "f2532eee272d45b1283ea4869d71f044",
  "name": "pycodestyle",
  "noarch": "python",
  "package_tarball_full_path": "/opt/homebrew/Caskroom/miniforge/base/pkgs/pycodestyle-2.8.0-pyhd8ed1ab_0.tar.bz2",
  "package_type": "noarch_python",
  "paths_data": {
    "paths": [
      {
        "_path": "site-packages/pycodestyle-2.8.0.dist-info/INSTALLER",
        "path_type": "hardlink",
        "sha256": "d0edee15f91b406f3f99726e44eb990be6e34fd0345b52b910c568e0eef6a2a8",
        "sha256_in_prefix": "d0edee15f91b406f3f99726e44eb990be6e34fd0345b52b910c568e0eef6a2a8",
        "size_in_bytes": 5
      },
      {
        "_path": "site-packages/pycodestyle-2.8.0.dist-info/LICENSE",
        "path_type": "hardlink",
        "sha256": "f772295e81af3478d34e88e52d076200230ec7dd6a39e123bc5cb35aa66abdae",
        "sha256_in_prefix": "f772295e81af3478d34e88e52d076200230ec7dd6a39e123bc5cb35aa66abdae",
        "size_in_bytes": 1254
      },
      {
        "_path": "site-packages/pycodestyle-2.8.0.dist-info/METADATA",
        "path_type": "hardlink",
        "sha256": "8cbc47832d72c2897462ed9cc6854b230e1730e9546945036628df4d4155dae6",
        "sha256_in_prefix": "8cbc47832d72c2897462ed9cc6854b230e1730e9546945036628df4d4155dae6",
        "size_in_bytes": 31230
      },
      {
        "_path": "site-packages/pycodestyle-2.8.0.dist-info/RECORD",
        "path_type": "hardlink",
        "sha256": "775ae7ad50808a579d4bafe4fc14be5b83c3ef453e8ddbf47275753b5b8dd5e4",
        "sha256_in_prefix": "775ae7ad50808a579d4bafe4fc14be5b83c3ef453e8ddbf47275753b5b8dd5e4",
        "size_in_bytes": 1099
      },
      {
        "_path": "site-packages/pycodestyle-2.8.0.dist-info/REQUESTED",
        "path_type": "hardlink",
        "sha256": "e3b0c44298fc1c149afbf4c8996fb92427ae41e4649b934ca495991b7852b855",
        "sha256_in_prefix": "e3b0c44298fc1c149afbf4c8996fb92427ae41e4649b934ca495991b7852b855",
        "size_in_bytes": 0
      },
      {
        "_path": "site-packages/pycodestyle-2.8.0.dist-info/WHEEL",
        "path_type": "hardlink",
        "sha256": "5b367c7308e1f25d23b542cd8d8ab51e9afe582a824603ebfbe4d7e0fe48d56a",
        "sha256_in_prefix": "5b367c7308e1f25d23b542cd8d8ab51e9afe582a824603ebfbe4d7e0fe48d56a",
        "size_in_bytes": 110
      },
      {
        "_path": "site-packages/pycodestyle-2.8.0.dist-info/direct_url.json",
        "path_type": "hardlink",
        "sha256": "47b05778398ddcd9b4a9d6951c0476a205cbecedb48606ee72b456f797835713",
        "sha256_in_prefix": "47b05778398ddcd9b4a9d6951c0476a205cbecedb48606ee72b456f797835713",
        "size_in_bytes": 107
      },
      {
        "_path": "site-packages/pycodestyle-2.8.0.dist-info/entry_points.txt",
        "path_type": "hardlink",
        "sha256": "e8953fed2029a42f773014908b5fd0c43c04414ca0e9c80aef569bf6afc7c5ca",
        "sha256_in_prefix": "e8953fed2029a42f773014908b5fd0c43c04414ca0e9c80aef569bf6afc7c5ca",
        "size_in_bytes": 51
      },
      {
        "_path": "site-packages/pycodestyle-2.8.0.dist-info/namespace_packages.txt",
        "path_type": "hardlink",
        "sha256": "01ba4719c80b6fe911b091a7c05124b64eeece964e09c058ef8f9805daca546b",
        "sha256_in_prefix": "01ba4719c80b6fe911b091a7c05124b64eeece964e09c058ef8f9805daca546b",
        "size_in_bytes": 1
      },
      {
        "_path": "site-packages/pycodestyle-2.8.0.dist-info/top_level.txt",
        "path_type": "hardlink",
        "sha256": "ac76c81225e6bec274d7a98570b55c17f77e74a80fdd575f381e8259b8af66e8",
        "sha256_in_prefix": "ac76c81225e6bec274d7a98570b55c17f77e74a80fdd575f381e8259b8af66e8",
        "size_in_bytes": 12
      },
      {
        "_path": "site-packages/pycodestyle.py",
        "path_type": "hardlink",
        "sha256": "dfe3b68b160b905a229b7f843755cbb472f6fa825a7dee8140aad8da76e4ac0e",
        "sha256_in_prefix": "dfe3b68b160b905a229b7f843755cbb472f6fa825a7dee8140aad8da76e4ac0e",
        "size_in_bytes": 105016
      },
      {
        "_path": "lib/python3.9/site-packages/__pycache__/pycodestyle.cpython-39.pyc",
        "path_type": "pyc_file"
      },
      {
        "_path": "bin/pycodestyle",
        "path_type": "unix_python_entry_point"
      }
    ],
    "paths_version": 1
  },
  "requested_spec": "None",
  "sha256": "1da7a030000a8858bf8f46d88e052b51a9296b65ef9bc540ae642729be2cf367",
  "size": 39924,
  "subdir": "noarch",
  "timestamp": 1633982586909,
  "track_features": "",
  "url": "https://conda.anaconda.org/conda-forge/noarch/pycodestyle-2.8.0-pyhd8ed1ab_0.tar.bz2",
  "version": "2.8.0"
}